simplifiedmc/__init__.py
simplifiedmc/emcee.py
simplifiedmc/shared.py
simplifiedmc/stan.py
simplifiedmc-1.0.1.data/scripts/smc-analyze
simplifiedmc-1.0.1.data/scripts/smc-emcee
simplifiedmc-1.0.1.data/scripts/smc-stan
simplifiedmc-1.0.1.dist-info/LICENSE.md
simplifiedmc-1.0.1.dist-info/METADATA
simplifiedmc-1.0.1.dist-info/WHEEL
simplifiedmc-1.0.1.dist-info/top_level.txt
simplifiedmc-1.0.1.dist-info/RECORD
