Metadata-Version: 2.1
Name: simplifiedmc
Version: 1.0.1
Summary: A CLI that simplifies the usage of MCMC methods.
Home-page: https://github.com/jpmvferreira/simplifiedmc
Author: José Ferreira
Author-email: jose@jpferreira.me
License: MIT
Platform: UNKNOWN
License-File: LICENSE.md
Requires-Dist: numpy
Requires-Dist: matplotlib
Requires-Dist: emcee
Requires-Dist: getdist
Requires-Dist: tqdm
Requires-Dist: h5py
Requires-Dist: arviz
Requires-Dist: pandas
Requires-Dist: pystan
Requires-Dist: pyyaml
